README.md
setup.py
incv_client/__init__.py
incv_client.egg-info/PKG-INFO
incv_client.egg-info/SOURCES.txt
incv_client.egg-info/dependency_links.txt
incv_client.egg-info/requires.txt
incv_client.egg-info/top_level.txt
incv_client/cos/__init__.py
incv_client/ius/__init__.py
incv_client/ius/ip_city.py
incv_client/tof/__init__.py
incv_client/tof/mail.py
incv_client/tof/sms.py
incv_client/tof/wx_robot.py