Metadata-Version: 2.1
Name: incv-client
Version: 0.0.9
Summary: An API Gateway Tool for INCV
Home-page: https://www.incv.net/
Author: Oren Zhang
Author-email: oren_zhang@outlook.com
License: UNKNOWN
Platform: UNKNOWN
